{
  "layer": "rss",
  "mode": "external",
  "window_days": 7,
  "pair_count": 75,
  "country_count": 20,
  "weights": {
    "direct": 0.5,
    "similarity": 0.3,
    "topic": 0.2
  },
  "pairs": [
    {
      "source": "HU",
      "target": "RU",
      "score": 98.25,
      "band": "very_high",
      "direct_score": 100.0,
      "similarity_score": 99.4,
      "topic_score": 92.17,
      "direct_weight": 32.0,
      "similarity_weight": 0.994
    },
    {
      "source": "HU",
      "target": "UA",
      "score": 78.99,
      "band": "high",
      "direct_score": 65.62,
      "similarity_score": 97.8,
      "topic_score": 84.17,
      "direct_weight": 21.0,
      "similarity_weight": 0.978
    },
    {
      "source": "FR",
      "target": "RU",
      "score": 62.94,
      "band": "high",
      "direct_score": 34.38,
      "similarity_score": 97.7,
      "topic_score": 82.24,
      "direct_weight": 11.0,
      "similarity_weight": 0.977
    },
    {
      "source": "FR",
      "target": "UA",
      "score": 58.52,
      "band": "medium",
      "direct_score": 25.0,
      "similarity_score": 97.1,
      "topic_score": 84.44,
      "direct_weight": 8.0,
      "similarity_weight": 0.971
    },
    {
      "source": "FI",
      "target": "UA",
      "score": 57.69,
      "band": "medium",
      "direct_score": 21.88,
      "similarity_score": 98.8,
      "topic_score": 85.56,
      "direct_weight": 7.0,
      "similarity_weight": 0.988
    },
    {
      "source": "DE",
      "target": "RU",
      "score": 51.52,
      "band": "medium",
      "direct_score": 25.0,
      "similarity_score": 85.7,
      "topic_score": 66.53,
      "direct_weight": 8.0,
      "similarity_weight": 0.857
    },
    {
      "source": "LV",
      "target": "RU",
      "score": 49.73,
      "band": "medium",
      "direct_score": 15.62,
      "similarity_score": 95.5,
      "topic_score": 66.33,
      "direct_weight": 5.0,
      "similarity_weight": 0.955
    },
    {
      "source": "PL",
      "target": "RU",
      "score": 49.25,
      "band": "medium",
      "direct_score": 6.25,
      "similarity_score": 97.3,
      "topic_score": 84.69,
      "direct_weight": 2.0,
      "similarity_weight": 0.973
    },
    {
      "source": "SK",
      "target": "UA",
      "score": 49.17,
      "band": "medium",
      "direct_score": 6.25,
      "similarity_score": 97.2,
      "topic_score": 84.44,
      "direct_weight": 2.0,
      "similarity_weight": 0.972
    },
    {
      "source": "RU",
      "target": "SK",
      "score": 48.59,
      "band": "medium",
      "direct_score": 9.38,
      "similarity_score": 94.1,
      "topic_score": 78.37,
      "direct_weight": 3.0,
      "similarity_weight": 0.941
    },
    {
      "source": "PL",
      "target": "UA",
      "score": 48.37,
      "band": "medium",
      "direct_score": 3.12,
      "similarity_score": 99.0,
      "topic_score": 85.56,
      "direct_weight": 1.0,
      "similarity_weight": 0.99
    },
    {
      "source": "EE",
      "target": "RU",
      "score": 48.17,
      "band": "medium",
      "direct_score": 12.5,
      "similarity_score": 95.5,
      "topic_score": 66.33,
      "direct_weight": 4.0,
      "similarity_weight": 0.955
    },
    {
      "source": "RU",
      "target": "SE",
      "score": 48.17,
      "band": "medium",
      "direct_score": 12.5,
      "similarity_score": 95.5,
      "topic_score": 66.33,
      "direct_weight": 4.0,
      "similarity_weight": 0.955
    },
    {
      "source": "DE",
      "target": "UA",
      "score": 48.02,
      "band": "medium",
      "direct_score": 12.5,
      "similarity_score": 89.9,
      "topic_score": 74.0,
      "direct_weight": 4.0,
      "similarity_weight": 0.899
    },
    {
      "source": "FI",
      "target": "RU",
      "score": 47.19,
      "band": "medium",
      "direct_score": 0.0,
      "similarity_score": 98.8,
      "topic_score": 87.76,
      "direct_weight": 0.0,
      "similarity_weight": 0.988
    },
    {
      "source": "CN",
      "target": "FR",
      "score": 46.86,
      "band": "medium",
      "direct_score": 12.5,
      "similarity_score": 89.7,
      "topic_score": 68.52,
      "direct_weight": 4.0,
      "similarity_weight": 0.897
    },
    {
      "source": "EE",
      "target": "UA",
      "score": 46.13,
      "band": "medium",
      "direct_score": 12.5,
      "similarity_score": 92.2,
      "topic_score": 61.11,
      "direct_weight": 4.0,
      "similarity_weight": 0.922
    },
    {
      "source": "LV",
      "target": "UA",
      "score": 46.13,
      "band": "medium",
      "direct_score": 12.5,
      "similarity_score": 92.2,
      "topic_score": 61.11,
      "direct_weight": 4.0,
      "similarity_weight": 0.922
    },
    {
      "source": "SE",
      "target": "UA",
      "score": 46.13,
      "band": "medium",
      "direct_score": 12.5,
      "similarity_score": 92.2,
      "topic_score": 61.11,
      "direct_weight": 4.0,
      "similarity_weight": 0.922
    },
    {
      "source": "CZ",
      "target": "RU",
      "score": 45.04,
      "band": "medium",
      "direct_score": 6.25,
      "similarity_score": 95.5,
      "topic_score": 66.33,
      "direct_weight": 2.0,
      "similarity_weight": 0.955
    },
    {
      "source": "IE",
      "target": "RU",
      "score": 43.22,
      "band": "medium",
      "direct_score": 6.25,
      "similarity_score": 87.4,
      "topic_score": 69.39,
      "direct_weight": 2.0,
      "similarity_weight": 0.874
    },
    {
      "source": "DE",
      "target": "TR",
      "score": 43.02,
      "band": "medium",
      "direct_score": 15.62,
      "similarity_score": 74.9,
      "topic_score": 63.69,
      "direct_weight": 5.0,
      "similarity_weight": 0.749
    },
    {
      "source": "LT",
      "target": "UA",
      "score": 42.74,
      "band": "medium",
      "direct_score": 12.5,
      "similarity_score": 79.4,
      "topic_score": 63.33,
      "direct_weight": 4.0,
      "similarity_weight": 0.794
    },
    {
      "source": "CN",
      "target": "PL",
      "score": 42.39,
      "band": "medium",
      "direct_score": 0.0,
      "similarity_score": 91.3,
      "topic_score": 75.0,
      "direct_weight": 0.0,
      "similarity_weight": 0.913
    },
    {
      "source": "CN",
      "target": "SK",
      "score": 42.18,
      "band": "medium",
      "direct_score": 0.0,
      "similarity_score": 90.6,
      "topic_score": 75.0,
      "direct_weight": 0.0,
      "similarity_weight": 0.906
    },
    {
      "source": "LT",
      "target": "TR",
      "score": 40.88,
      "band": "medium",
      "direct_score": 0.0,
      "similarity_score": 86.7,
      "topic_score": 74.36,
      "direct_weight": 0.0,
      "similarity_weight": 0.867
    },
    {
      "source": "CN",
      "target": "FI",
      "score": 40.67,
      "band": "medium",
      "direct_score": 0.0,
      "similarity_score": 88.9,
      "topic_score": 70.0,
      "direct_weight": 0.0,
      "similarity_weight": 0.889
    },
    {
      "source": "LT",
      "target": "RU",
      "score": 40.02,
      "band": "medium",
      "direct_score": 12.5,
      "similarity_score": 74.7,
      "topic_score": 56.8,
      "direct_weight": 4.0,
      "similarity_weight": 0.747
    },
    {
      "source": "CZ",
      "target": "UA",
      "score": 39.88,
      "band": "low",
      "direct_score": 0.0,
      "similarity_score": 92.2,
      "topic_score": 61.11,
      "direct_weight": 0.0,
      "similarity_weight": 0.922
    },
    {
      "source": "CN",
      "target": "HU",
      "score": 39.53,
      "band": "low",
      "direct_score": 0.0,
      "similarity_score": 87.5,
      "topic_score": 66.39,
      "direct_weight": 0.0,
      "similarity_weight": 0.875
    },
    {
      "source": "IE",
      "target": "US",
      "score": 38.9,
      "band": "low",
      "direct_score": 3.12,
      "similarity_score": 80.0,
      "topic_score": 66.67,
      "direct_weight": 1.0,
      "similarity_weight": 0.8
    },
    {
      "source": "IE",
      "target": "UA",
      "score": 38.76,
      "band": "low",
      "direct_score": 0.0,
      "similarity_score": 85.5,
      "topic_score": 65.56,
      "direct_weight": 0.0,
      "similarity_weight": 0.855
    },
    {
      "source": "GB",
      "target": "LT",
      "score": 38.32,
      "band": "low",
      "direct_score": 0.0,
      "similarity_score": 83.3,
      "topic_score": 66.67,
      "direct_weight": 0.0,
      "similarity_weight": 0.833
    },
    {
      "source": "GR",
      "target": "TR",
      "score": 38.13,
      "band": "low",
      "direct_score": 6.25,
      "similarity_score": 80.8,
      "topic_score": 53.85,
      "direct_weight": 2.0,
      "similarity_weight": 0.808
    },
    {
      "source": "CN",
      "target": "DE",
      "score": 37.18,
      "band": "low",
      "direct_score": 0.0,
      "similarity_score": 80.6,
      "topic_score": 65.0,
      "direct_weight": 0.0,
      "similarity_weight": 0.806
    },
    {
      "source": "GB",
      "target": "GR",
      "score": 35.98,
      "band": "low",
      "direct_score": 0.0,
      "similarity_score": 86.6,
      "topic_score": 50.0,
      "direct_weight": 0.0,
      "similarity_weight": 0.866
    },
    {
      "source": "DE",
      "target": "GB",
      "score": 34.86,
      "band": "low",
      "direct_score": 0.0,
      "similarity_score": 75.3,
      "topic_score": 61.33,
      "direct_weight": 0.0,
      "similarity_weight": 0.753
    },
    {
      "source": "CN",
      "target": "CZ",
      "score": 34.48,
      "band": "low",
      "direct_score": 0.0,
      "similarity_score": 81.6,
      "topic_score": 50.0,
      "direct_weight": 0.0,
      "similarity_weight": 0.816
    },
    {
      "source": "CN",
      "target": "EE",
      "score": 34.48,
      "band": "low",
      "direct_score": 0.0,
      "similarity_score": 81.6,
      "topic_score": 50.0,
      "direct_weight": 0.0,
      "similarity_weight": 0.816
    },
    {
      "source": "CN",
      "target": "LV",
      "score": 34.48,
      "band": "low",
      "direct_score": 0.0,
      "similarity_score": 81.6,
      "topic_score": 50.0,
      "direct_weight": 0.0,
      "similarity_weight": 0.816
    },
    {
      "source": "CN",
      "target": "SE",
      "score": 34.48,
      "band": "low",
      "direct_score": 0.0,
      "similarity_score": 81.6,
      "topic_score": 50.0,
      "direct_weight": 0.0,
      "similarity_weight": 0.816
    },
    {
      "source": "CN",
      "target": "LT",
      "score": 32.88,
      "band": "low",
      "direct_score": 0.0,
      "similarity_score": 70.7,
      "topic_score": 58.33,
      "direct_weight": 0.0,
      "similarity_weight": 0.707
    },
    {
      "source": "CN",
      "target": "IE",
      "score": 31.9,
      "band": "low",
      "direct_score": 0.0,
      "similarity_score": 73.0,
      "topic_score": 50.0,
      "direct_weight": 0.0,
      "similarity_weight": 0.73
    },
    {
      "source": "FR",
      "target": "GB",
      "score": 30.63,
      "band": "low",
      "direct_score": 12.5,
      "similarity_score": 50.4,
      "topic_score": 46.3,
      "direct_weight": 4.0,
      "similarity_weight": 0.504
    },
    {
      "source": "GB",
      "target": "IT",
      "score": 30.01,
      "band": "low",
      "direct_score": 0.0,
      "similarity_score": 66.7,
      "topic_score": 50.0,
      "direct_weight": 0.0,
      "similarity_weight": 0.667
    },
    {
      "source": "IT",
      "target": "UA",
      "score": 29.35,
      "band": "low",
      "direct_score": 6.25,
      "similarity_score": 60.0,
      "topic_score": 41.11,
      "direct_weight": 2.0,
      "similarity_weight": 0.6
    },
    {
      "source": "IT",
      "target": "RU",
      "score": 28.71,
      "band": "low",
      "direct_score": 0.0,
      "similarity_score": 65.3,
      "topic_score": 45.58,
      "direct_weight": 0.0,
      "similarity_weight": 0.653
    },
    {
      "source": "IT",
      "target": "TR",
      "score": 27.32,
      "band": "low",
      "direct_score": 6.25,
      "similarity_score": 53.3,
      "topic_score": 41.03,
      "direct_weight": 2.0,
      "similarity_weight": 0.533
    },
    {
      "source": "FI",
      "target": "US",
      "score": 26.67,
      "band": "low",
      "direct_score": 3.12,
      "similarity_score": 54.8,
      "topic_score": 43.33,
      "direct_weight": 1.0,
      "similarity_weight": 0.548
    },
    {
      "source": "FR",
      "target": "US",
      "score": 25.58,
      "band": "low",
      "direct_score": 3.12,
      "similarity_score": 52.9,
      "topic_score": 40.74,
      "direct_weight": 1.0,
      "similarity_weight": 0.529
    },
    {
      "source": "HU",
      "target": "US",
      "score": 24.87,
      "band": "low",
      "direct_score": 3.12,
      "similarity_score": 51.1,
      "topic_score": 39.89,
      "direct_weight": 1.0,
      "similarity_weight": 0.511
    },
    {
      "source": "SK",
      "target": "TR",
      "score": 23.27,
      "band": "low",
      "direct_score": 3.12,
      "similarity_score": 41.6,
      "topic_score": 46.15,
      "direct_weight": 1.0,
      "similarity_weight": 0.416
    },
    {
      "source": "CN",
      "target": "IT",
      "score": 20.8,
      "band": "low",
      "direct_score": 0.0,
      "similarity_score": 47.1,
      "topic_score": 33.33,
      "direct_weight": 0.0,
      "similarity_weight": 0.471
    },
    {
      "source": "FI",
      "target": "GB",
      "score": 20.46,
      "band": "low",
      "direct_score": 0.0,
      "similarity_score": 39.3,
      "topic_score": 43.33,
      "direct_weight": 0.0,
      "similarity_weight": 0.393
    },
    {
      "source": "CZ",
      "target": "US",
      "score": 20.08,
      "band": "low",
      "direct_score": 0.0,
      "similarity_score": 44.7,
      "topic_score": 33.33,
      "direct_weight": 0.0,
      "similarity_weight": 0.447
    },
    {
      "source": "EE",
      "target": "US",
      "score": 20.08,
      "band": "low",
      "direct_score": 0.0,
      "similarity_score": 44.7,
      "topic_score": 33.33,
      "direct_weight": 0.0,
      "similarity_weight": 0.447
    },
    {
      "source": "LV",
      "target": "US",
      "score": 20.08,
      "band": "low",
      "direct_score": 0.0,
      "similarity_score": 44.7,
      "topic_score": 33.33,
      "direct_weight": 0.0,
      "similarity_weight": 0.447
    },
    {
      "source": "SE",
      "target": "US",
      "score": 20.08,
      "band": "low",
      "direct_score": 0.0,
      "similarity_score": 44.7,
      "topic_score": 33.33,
      "direct_weight": 0.0,
      "similarity_weight": 0.447
    },
    {
      "source": "GB",
      "target": "HU",
      "score": 19.05,
      "band": "very_low",
      "direct_score": 0.0,
      "similarity_score": 37.1,
      "topic_score": 39.62,
      "direct_weight": 0.0,
      "similarity_weight": 0.371
    },
    {
      "source": "PL",
      "target": "TR",
      "score": 19.04,
      "band": "very_low",
      "direct_score": 0.0,
      "similarity_score": 36.1,
      "topic_score": 41.03,
      "direct_weight": 0.0,
      "similarity_weight": 0.361
    },
    {
      "source": "DE",
      "target": "US",
      "score": 18.84,
      "band": "very_low",
      "direct_score": 0.0,
      "similarity_score": 37.9,
      "topic_score": 37.33,
      "direct_weight": 0.0,
      "similarity_weight": 0.379
    },
    {
      "source": "GB",
      "target": "SK",
      "score": 18.67,
      "band": "very_low",
      "direct_score": 0.0,
      "similarity_score": 40.0,
      "topic_score": 33.33,
      "direct_weight": 0.0,
      "similarity_weight": 0.4
    },
    {
      "source": "PL",
      "target": "US",
      "score": 18.67,
      "band": "very_low",
      "direct_score": 0.0,
      "similarity_score": 40.0,
      "topic_score": 33.33,
      "direct_weight": 0.0,
      "similarity_weight": 0.4
    },
    {
      "source": "GB",
      "target": "IE",
      "score": 18.28,
      "band": "very_low",
      "direct_score": 0.0,
      "similarity_score": 38.7,
      "topic_score": 33.33,
      "direct_weight": 0.0,
      "similarity_weight": 0.387
    },
    {
      "source": "GB",
      "target": "PL",
      "score": 18.28,
      "band": "very_low",
      "direct_score": 0.0,
      "similarity_score": 38.7,
      "topic_score": 33.33,
      "direct_weight": 0.0,
      "similarity_weight": 0.387
    },
    {
      "source": "SK",
      "target": "US",
      "score": 17.83,
      "band": "very_low",
      "direct_score": 0.0,
      "similarity_score": 37.2,
      "topic_score": 33.33,
      "direct_weight": 0.0,
      "similarity_weight": 0.372
    },
    {
      "source": "FR",
      "target": "TR",
      "score": 16.33,
      "band": "very_low",
      "direct_score": 0.0,
      "similarity_score": 34.5,
      "topic_score": 29.91,
      "direct_weight": 0.0,
      "similarity_weight": 0.345
    },
    {
      "source": "IT",
      "target": "US",
      "score": 14.41,
      "band": "very_low",
      "direct_score": 0.0,
      "similarity_score": 25.8,
      "topic_score": 33.33,
      "direct_weight": 0.0,
      "similarity_weight": 0.258
    },
    {
      "source": "LT",
      "target": "US",
      "score": 14.41,
      "band": "very_low",
      "direct_score": 0.0,
      "similarity_score": 25.8,
      "topic_score": 33.33,
      "direct_weight": 0.0,
      "similarity_weight": 0.258
    },
    {
      "source": "HU",
      "target": "TR",
      "score": 13.79,
      "band": "very_low",
      "direct_score": 3.12,
      "similarity_score": 24.7,
      "topic_score": 24.09,
      "direct_weight": 1.0,
      "similarity_weight": 0.247
    },
    {
      "source": "FI",
      "target": "TR",
      "score": 13.55,
      "band": "very_low",
      "direct_score": 0.0,
      "similarity_score": 26.7,
      "topic_score": 27.69,
      "direct_weight": 0.0,
      "similarity_weight": 0.267
    },
    {
      "source": "CZ",
      "target": "GB",
      "score": 12.0,
      "band": "very_low",
      "direct_score": 0.0,
      "similarity_score": 28.9,
      "topic_score": 16.67,
      "direct_weight": 0.0,
      "similarity_weight": 0.289
    },
    {
      "source": "EE",
      "target": "GB",
      "score": 12.0,
      "band": "very_low",
      "direct_score": 0.0,
      "similarity_score": 28.9,
      "topic_score": 16.67,
      "direct_weight": 0.0,
      "similarity_weight": 0.289
    },
    {
      "source": "GB",
      "target": "LV",
      "score": 12.0,
      "band": "very_low",
      "direct_score": 0.0,
      "similarity_score": 28.9,
      "topic_score": 16.67,
      "direct_weight": 0.0,
      "similarity_weight": 0.289
    },
    {
      "source": "GB",
      "target": "SE",
      "score": 12.0,
      "band": "very_low",
      "direct_score": 0.0,
      "similarity_score": 28.9,
      "topic_score": 16.67,
      "direct_weight": 0.0,
      "similarity_weight": 0.289
    }
  ],
  "by_country": [
    {
      "country": "RU",
      "relationship_count": 13,
      "average_score": 50.83,
      "strongest_partner": "HU",
      "strongest_score": 98.25,
      "top_partners": [
        {
          "partner": "HU",
          "score": 98.25,
          "band": "very_high",
          "direct_score": 100.0,
          "similarity_score": 99.4,
          "topic_score": 92.17
        },
        {
          "partner": "FR",
          "score": 62.94,
          "band": "high",
          "direct_score": 34.38,
          "similarity_score": 97.7,
          "topic_score": 82.24
        },
        {
          "partner": "DE",
          "score": 51.52,
          "band": "medium",
          "direct_score": 25.0,
          "similarity_score": 85.7,
          "topic_score": 66.53
        },
        {
          "partner": "LV",
          "score": 49.73,
          "band": "medium",
          "direct_score": 15.62,
          "similarity_score": 95.5,
          "topic_score": 66.33
        },
        {
          "partner": "PL",
          "score": 49.25,
          "band": "medium",
          "direct_score": 6.25,
          "similarity_score": 97.3,
          "topic_score": 84.69
        },
        {
          "partner": "SK",
          "score": 48.59,
          "band": "medium",
          "direct_score": 9.38,
          "similarity_score": 94.1,
          "topic_score": 78.37
        },
        {
          "partner": "EE",
          "score": 48.17,
          "band": "medium",
          "direct_score": 12.5,
          "similarity_score": 95.5,
          "topic_score": 66.33
        },
        {
          "partner": "SE",
          "score": 48.17,
          "band": "medium",
          "direct_score": 12.5,
          "similarity_score": 95.5,
          "topic_score": 66.33
        },
        {
          "partner": "FI",
          "score": 47.19,
          "band": "medium",
          "direct_score": 0.0,
          "similarity_score": 98.8,
          "topic_score": 87.76
        },
        {
          "partner": "CZ",
          "score": 45.04,
          "band": "medium",
          "direct_score": 6.25,
          "similarity_score": 95.5,
          "topic_score": 66.33
        }
      ]
    },
    {
      "country": "UA",
      "relationship_count": 13,
      "average_score": 48.45,
      "strongest_partner": "HU",
      "strongest_score": 78.99,
      "top_partners": [
        {
          "partner": "HU",
          "score": 78.99,
          "band": "high",
          "direct_score": 65.62,
          "similarity_score": 97.8,
          "topic_score": 84.17
        },
        {
          "partner": "FR",
          "score": 58.52,
          "band": "medium",
          "direct_score": 25.0,
          "similarity_score": 97.1,
          "topic_score": 84.44
        },
        {
          "partner": "FI",
          "score": 57.69,
          "band": "medium",
          "direct_score": 21.88,
          "similarity_score": 98.8,
          "topic_score": 85.56
        },
        {
          "partner": "SK",
          "score": 49.17,
          "band": "medium",
          "direct_score": 6.25,
          "similarity_score": 97.2,
          "topic_score": 84.44
        },
        {
          "partner": "PL",
          "score": 48.37,
          "band": "medium",
          "direct_score": 3.12,
          "similarity_score": 99.0,
          "topic_score": 85.56
        },
        {
          "partner": "DE",
          "score": 48.02,
          "band": "medium",
          "direct_score": 12.5,
          "similarity_score": 89.9,
          "topic_score": 74.0
        },
        {
          "partner": "EE",
          "score": 46.13,
          "band": "medium",
          "direct_score": 12.5,
          "similarity_score": 92.2,
          "topic_score": 61.11
        },
        {
          "partner": "LV",
          "score": 46.13,
          "band": "medium",
          "direct_score": 12.5,
          "similarity_score": 92.2,
          "topic_score": 61.11
        },
        {
          "partner": "SE",
          "score": 46.13,
          "band": "medium",
          "direct_score": 12.5,
          "similarity_score": 92.2,
          "topic_score": 61.11
        },
        {
          "partner": "LT",
          "score": 42.74,
          "band": "medium",
          "direct_score": 12.5,
          "similarity_score": 79.4,
          "topic_score": 63.33
        }
      ]
    },
    {
      "country": "HU",
      "relationship_count": 6,
      "average_score": 45.75,
      "strongest_partner": "RU",
      "strongest_score": 98.25,
      "top_partners": [
        {
          "partner": "RU",
          "score": 98.25,
          "band": "very_high",
          "direct_score": 100.0,
          "similarity_score": 99.4,
          "topic_score": 92.17
        },
        {
          "partner": "UA",
          "score": 78.99,
          "band": "high",
          "direct_score": 65.62,
          "similarity_score": 97.8,
          "topic_score": 84.17
        },
        {
          "partner": "CN",
          "score": 39.53,
          "band": "low",
          "direct_score": 0.0,
          "similarity_score": 87.5,
          "topic_score": 66.39
        },
        {
          "partner": "US",
          "score": 24.87,
          "band": "low",
          "direct_score": 3.12,
          "similarity_score": 51.1,
          "topic_score": 39.89
        },
        {
          "partner": "GB",
          "score": 19.05,
          "band": "very_low",
          "direct_score": 0.0,
          "similarity_score": 37.1,
          "topic_score": 39.62
        },
        {
          "partner": "TR",
          "score": 13.79,
          "band": "very_low",
          "direct_score": 3.12,
          "similarity_score": 24.7,
          "topic_score": 24.09
        }
      ]
    },
    {
      "country": "FR",
      "relationship_count": 6,
      "average_score": 40.14,
      "strongest_partner": "RU",
      "strongest_score": 62.94,
      "top_partners": [
        {
          "partner": "RU",
          "score": 62.94,
          "band": "high",
          "direct_score": 34.38,
          "similarity_score": 97.7,
          "topic_score": 82.24
        },
        {
          "partner": "UA",
          "score": 58.52,
          "band": "medium",
          "direct_score": 25.0,
          "similarity_score": 97.1,
          "topic_score": 84.44
        },
        {
          "partner": "CN",
          "score": 46.86,
          "band": "medium",
          "direct_score": 12.5,
          "similarity_score": 89.7,
          "topic_score": 68.52
        },
        {
          "partner": "GB",
          "score": 30.63,
          "band": "low",
          "direct_score": 12.5,
          "similarity_score": 50.4,
          "topic_score": 46.3
        },
        {
          "partner": "US",
          "score": 25.58,
          "band": "low",
          "direct_score": 3.12,
          "similarity_score": 52.9,
          "topic_score": 40.74
        },
        {
          "partner": "TR",
          "score": 16.33,
          "band": "very_low",
          "direct_score": 0.0,
          "similarity_score": 34.5,
          "topic_score": 29.91
        }
      ]
    },
    {
      "country": "DE",
      "relationship_count": 6,
      "average_score": 38.91,
      "strongest_partner": "RU",
      "strongest_score": 51.52,
      "top_partners": [
        {
          "partner": "RU",
          "score": 51.52,
          "band": "medium",
          "direct_score": 25.0,
          "similarity_score": 85.7,
          "topic_score": 66.53
        },
        {
          "partner": "UA",
          "score": 48.02,
          "band": "medium",
          "direct_score": 12.5,
          "similarity_score": 89.9,
          "topic_score": 74.0
        },
        {
          "partner": "TR",
          "score": 43.02,
          "band": "medium",
          "direct_score": 15.62,
          "similarity_score": 74.9,
          "topic_score": 63.69
        },
        {
          "partner": "CN",
          "score": 37.18,
          "band": "low",
          "direct_score": 0.0,
          "similarity_score": 80.6,
          "topic_score": 65.0
        },
        {
          "partner": "GB",
          "score": 34.86,
          "band": "low",
          "direct_score": 0.0,
          "similarity_score": 75.3,
          "topic_score": 61.33
        },
        {
          "partner": "US",
          "score": 18.84,
          "band": "very_low",
          "direct_score": 0.0,
          "similarity_score": 37.9,
          "topic_score": 37.33
        }
      ]
    },
    {
      "country": "GR",
      "relationship_count": 2,
      "average_score": 37.05,
      "strongest_partner": "TR",
      "strongest_score": 38.13,
      "top_partners": [
        {
          "partner": "TR",
          "score": 38.13,
          "band": "low",
          "direct_score": 6.25,
          "similarity_score": 80.8,
          "topic_score": 53.85
        },
        {
          "partner": "GB",
          "score": 35.98,
          "band": "low",
          "direct_score": 0.0,
          "similarity_score": 86.6,
          "topic_score": 50.0
        }
      ]
    },
    {
      "country": "CN",
      "relationship_count": 13,
      "average_score": 36.33,
      "strongest_partner": "FR",
      "strongest_score": 46.86,
      "top_partners": [
        {
          "partner": "FR",
          "score": 46.86,
          "band": "medium",
          "direct_score": 12.5,
          "similarity_score": 89.7,
          "topic_score": 68.52
        },
        {
          "partner": "PL",
          "score": 42.39,
          "band": "medium",
          "direct_score": 0.0,
          "similarity_score": 91.3,
          "topic_score": 75.0
        },
        {
          "partner": "SK",
          "score": 42.18,
          "band": "medium",
          "direct_score": 0.0,
          "similarity_score": 90.6,
          "topic_score": 75.0
        },
        {
          "partner": "FI",
          "score": 40.67,
          "band": "medium",
          "direct_score": 0.0,
          "similarity_score": 88.9,
          "topic_score": 70.0
        },
        {
          "partner": "HU",
          "score": 39.53,
          "band": "low",
          "direct_score": 0.0,
          "similarity_score": 87.5,
          "topic_score": 66.39
        },
        {
          "partner": "DE",
          "score": 37.18,
          "band": "low",
          "direct_score": 0.0,
          "similarity_score": 80.6,
          "topic_score": 65.0
        },
        {
          "partner": "CZ",
          "score": 34.48,
          "band": "low",
          "direct_score": 0.0,
          "similarity_score": 81.6,
          "topic_score": 50.0
        },
        {
          "partner": "EE",
          "score": 34.48,
          "band": "low",
          "direct_score": 0.0,
          "similarity_score": 81.6,
          "topic_score": 50.0
        },
        {
          "partner": "LV",
          "score": 34.48,
          "band": "low",
          "direct_score": 0.0,
          "similarity_score": 81.6,
          "topic_score": 50.0
        },
        {
          "partner": "SE",
          "score": 34.48,
          "band": "low",
          "direct_score": 0.0,
          "similarity_score": 81.6,
          "topic_score": 50.0
        }
      ]
    },
    {
      "country": "LT",
      "relationship_count": 6,
      "average_score": 34.88,
      "strongest_partner": "UA",
      "strongest_score": 42.74,
      "top_partners": [
        {
          "partner": "UA",
          "score": 42.74,
          "band": "medium",
          "direct_score": 12.5,
          "similarity_score": 79.4,
          "topic_score": 63.33
        },
        {
          "partner": "TR",
          "score": 40.88,
          "band": "medium",
          "direct_score": 0.0,
          "similarity_score": 86.7,
          "topic_score": 74.36
        },
        {
          "partner": "RU",
          "score": 40.02,
          "band": "medium",
          "direct_score": 12.5,
          "similarity_score": 74.7,
          "topic_score": 56.8
        },
        {
          "partner": "GB",
          "score": 38.32,
          "band": "low",
          "direct_score": 0.0,
          "similarity_score": 83.3,
          "topic_score": 66.67
        },
        {
          "partner": "CN",
          "score": 32.88,
          "band": "low",
          "direct_score": 0.0,
          "similarity_score": 70.7,
          "topic_score": 58.33
        },
        {
          "partner": "US",
          "score": 14.41,
          "band": "very_low",
          "direct_score": 0.0,
          "similarity_score": 25.8,
          "topic_score": 33.33
        }
      ]
    },
    {
      "country": "FI",
      "relationship_count": 6,
      "average_score": 34.37,
      "strongest_partner": "UA",
      "strongest_score": 57.69,
      "top_partners": [
        {
          "partner": "UA",
          "score": 57.69,
          "band": "medium",
          "direct_score": 21.88,
          "similarity_score": 98.8,
          "topic_score": 85.56
        },
        {
          "partner": "RU",
          "score": 47.19,
          "band": "medium",
          "direct_score": 0.0,
          "similarity_score": 98.8,
          "topic_score": 87.76
        },
        {
          "partner": "CN",
          "score": 40.67,
          "band": "medium",
          "direct_score": 0.0,
          "similarity_score": 88.9,
          "topic_score": 70.0
        },
        {
          "partner": "US",
          "score": 26.67,
          "band": "low",
          "direct_score": 3.12,
          "similarity_score": 54.8,
          "topic_score": 43.33
        },
        {
          "partner": "GB",
          "score": 20.46,
          "band": "low",
          "direct_score": 0.0,
          "similarity_score": 39.3,
          "topic_score": 43.33
        },
        {
          "partner": "TR",
          "score": 13.55,
          "band": "very_low",
          "direct_score": 0.0,
          "similarity_score": 26.7,
          "topic_score": 27.69
        }
      ]
    },
    {
      "country": "IE",
      "relationship_count": 5,
      "average_score": 34.21,
      "strongest_partner": "RU",
      "strongest_score": 43.22,
      "top_partners": [
        {
          "partner": "RU",
          "score": 43.22,
          "band": "medium",
          "direct_score": 6.25,
          "similarity_score": 87.4,
          "topic_score": 69.39
        },
        {
          "partner": "US",
          "score": 38.9,
          "band": "low",
          "direct_score": 3.12,
          "similarity_score": 80.0,
          "topic_score": 66.67
        },
        {
          "partner": "UA",
          "score": 38.76,
          "band": "low",
          "direct_score": 0.0,
          "similarity_score": 85.5,
          "topic_score": 65.56
        },
        {
          "partner": "CN",
          "score": 31.9,
          "band": "low",
          "direct_score": 0.0,
          "similarity_score": 73.0,
          "topic_score": 50.0
        },
        {
          "partner": "GB",
          "score": 18.28,
          "band": "very_low",
          "direct_score": 0.0,
          "similarity_score": 38.7,
          "topic_score": 33.33
        }
      ]
    },
    {
      "country": "SK",
      "relationship_count": 6,
      "average_score": 33.28,
      "strongest_partner": "UA",
      "strongest_score": 49.17,
      "top_partners": [
        {
          "partner": "UA",
          "score": 49.17,
          "band": "medium",
          "direct_score": 6.25,
          "similarity_score": 97.2,
          "topic_score": 84.44
        },
        {
          "partner": "RU",
          "score": 48.59,
          "band": "medium",
          "direct_score": 9.38,
          "similarity_score": 94.1,
          "topic_score": 78.37
        },
        {
          "partner": "CN",
          "score": 42.18,
          "band": "medium",
          "direct_score": 0.0,
          "similarity_score": 90.6,
          "topic_score": 75.0
        },
        {
          "partner": "TR",
          "score": 23.27,
          "band": "low",
          "direct_score": 3.12,
          "similarity_score": 41.6,
          "topic_score": 46.15
        },
        {
          "partner": "GB",
          "score": 18.67,
          "band": "very_low",
          "direct_score": 0.0,
          "similarity_score": 40.0,
          "topic_score": 33.33
        },
        {
          "partner": "US",
          "score": 17.83,
          "band": "very_low",
          "direct_score": 0.0,
          "similarity_score": 37.2,
          "topic_score": 33.33
        }
      ]
    },
    {
      "country": "PL",
      "relationship_count": 6,
      "average_score": 32.67,
      "strongest_partner": "RU",
      "strongest_score": 49.25,
      "top_partners": [
        {
          "partner": "RU",
          "score": 49.25,
          "band": "medium",
          "direct_score": 6.25,
          "similarity_score": 97.3,
          "topic_score": 84.69
        },
        {
          "partner": "UA",
          "score": 48.37,
          "band": "medium",
          "direct_score": 3.12,
          "similarity_score": 99.0,
          "topic_score": 85.56
        },
        {
          "partner": "CN",
          "score": 42.39,
          "band": "medium",
          "direct_score": 0.0,
          "similarity_score": 91.3,
          "topic_score": 75.0
        },
        {
          "partner": "TR",
          "score": 19.04,
          "band": "very_low",
          "direct_score": 0.0,
          "similarity_score": 36.1,
          "topic_score": 41.03
        },
        {
          "partner": "US",
          "score": 18.67,
          "band": "very_low",
          "direct_score": 0.0,
          "similarity_score": 40.0,
          "topic_score": 33.33
        },
        {
          "partner": "GB",
          "score": 18.28,
          "band": "very_low",
          "direct_score": 0.0,
          "similarity_score": 38.7,
          "topic_score": 33.33
        }
      ]
    },
    {
      "country": "LV",
      "relationship_count": 5,
      "average_score": 32.48,
      "strongest_partner": "RU",
      "strongest_score": 49.73,
      "top_partners": [
        {
          "partner": "RU",
          "score": 49.73,
          "band": "medium",
          "direct_score": 15.62,
          "similarity_score": 95.5,
          "topic_score": 66.33
        },
        {
          "partner": "UA",
          "score": 46.13,
          "band": "medium",
          "direct_score": 12.5,
          "similarity_score": 92.2,
          "topic_score": 61.11
        },
        {
          "partner": "CN",
          "score": 34.48,
          "band": "low",
          "direct_score": 0.0,
          "similarity_score": 81.6,
          "topic_score": 50.0
        },
        {
          "partner": "US",
          "score": 20.08,
          "band": "low",
          "direct_score": 0.0,
          "similarity_score": 44.7,
          "topic_score": 33.33
        },
        {
          "partner": "GB",
          "score": 12.0,
          "band": "very_low",
          "direct_score": 0.0,
          "similarity_score": 28.9,
          "topic_score": 16.67
        }
      ]
    },
    {
      "country": "EE",
      "relationship_count": 5,
      "average_score": 32.17,
      "strongest_partner": "RU",
      "strongest_score": 48.17,
      "top_partners": [
        {
          "partner": "RU",
          "score": 48.17,
          "band": "medium",
          "direct_score": 12.5,
          "similarity_score": 95.5,
          "topic_score": 66.33
        },
        {
          "partner": "UA",
          "score": 46.13,
          "band": "medium",
          "direct_score": 12.5,
          "similarity_score": 92.2,
          "topic_score": 61.11
        },
        {
          "partner": "CN",
          "score": 34.48,
          "band": "low",
          "direct_score": 0.0,
          "similarity_score": 81.6,
          "topic_score": 50.0
        },
        {
          "partner": "US",
          "score": 20.08,
          "band": "low",
          "direct_score": 0.0,
          "similarity_score": 44.7,
          "topic_score": 33.33
        },
        {
          "partner": "GB",
          "score": 12.0,
          "band": "very_low",
          "direct_score": 0.0,
          "similarity_score": 28.9,
          "topic_score": 16.67
        }
      ]
    },
    {
      "country": "SE",
      "relationship_count": 5,
      "average_score": 32.17,
      "strongest_partner": "RU",
      "strongest_score": 48.17,
      "top_partners": [
        {
          "partner": "RU",
          "score": 48.17,
          "band": "medium",
          "direct_score": 12.5,
          "similarity_score": 95.5,
          "topic_score": 66.33
        },
        {
          "partner": "UA",
          "score": 46.13,
          "band": "medium",
          "direct_score": 12.5,
          "similarity_score": 92.2,
          "topic_score": 61.11
        },
        {
          "partner": "CN",
          "score": 34.48,
          "band": "low",
          "direct_score": 0.0,
          "similarity_score": 81.6,
          "topic_score": 50.0
        },
        {
          "partner": "US",
          "score": 20.08,
          "band": "low",
          "direct_score": 0.0,
          "similarity_score": 44.7,
          "topic_score": 33.33
        },
        {
          "partner": "GB",
          "score": 12.0,
          "band": "very_low",
          "direct_score": 0.0,
          "similarity_score": 28.9,
          "topic_score": 16.67
        }
      ]
    },
    {
      "country": "CZ",
      "relationship_count": 5,
      "average_score": 30.3,
      "strongest_partner": "RU",
      "strongest_score": 45.04,
      "top_partners": [
        {
          "partner": "RU",
          "score": 45.04,
          "band": "medium",
          "direct_score": 6.25,
          "similarity_score": 95.5,
          "topic_score": 66.33
        },
        {
          "partner": "UA",
          "score": 39.88,
          "band": "low",
          "direct_score": 0.0,
          "similarity_score": 92.2,
          "topic_score": 61.11
        },
        {
          "partner": "CN",
          "score": 34.48,
          "band": "low",
          "direct_score": 0.0,
          "similarity_score": 81.6,
          "topic_score": 50.0
        },
        {
          "partner": "US",
          "score": 20.08,
          "band": "low",
          "direct_score": 0.0,
          "similarity_score": 44.7,
          "topic_score": 33.33
        },
        {
          "partner": "GB",
          "score": 12.0,
          "band": "very_low",
          "direct_score": 0.0,
          "similarity_score": 28.9,
          "topic_score": 16.67
        }
      ]
    },
    {
      "country": "TR",
      "relationship_count": 9,
      "average_score": 26.15,
      "strongest_partner": "DE",
      "strongest_score": 43.02,
      "top_partners": [
        {
          "partner": "DE",
          "score": 43.02,
          "band": "medium",
          "direct_score": 15.62,
          "similarity_score": 74.9,
          "topic_score": 63.69
        },
        {
          "partner": "LT",
          "score": 40.88,
          "band": "medium",
          "direct_score": 0.0,
          "similarity_score": 86.7,
          "topic_score": 74.36
        },
        {
          "partner": "GR",
          "score": 38.13,
          "band": "low",
          "direct_score": 6.25,
          "similarity_score": 80.8,
          "topic_score": 53.85
        },
        {
          "partner": "IT",
          "score": 27.32,
          "band": "low",
          "direct_score": 6.25,
          "similarity_score": 53.3,
          "topic_score": 41.03
        },
        {
          "partner": "SK",
          "score": 23.27,
          "band": "low",
          "direct_score": 3.12,
          "similarity_score": 41.6,
          "topic_score": 46.15
        },
        {
          "partner": "PL",
          "score": 19.04,
          "band": "very_low",
          "direct_score": 0.0,
          "similarity_score": 36.1,
          "topic_score": 41.03
        },
        {
          "partner": "FR",
          "score": 16.33,
          "band": "very_low",
          "direct_score": 0.0,
          "similarity_score": 34.5,
          "topic_score": 29.91
        },
        {
          "partner": "HU",
          "score": 13.79,
          "band": "very_low",
          "direct_score": 3.12,
          "similarity_score": 24.7,
          "topic_score": 24.09
        },
        {
          "partner": "FI",
          "score": 13.55,
          "band": "very_low",
          "direct_score": 0.0,
          "similarity_score": 26.7,
          "topic_score": 27.69
        }
      ]
    },
    {
      "country": "IT",
      "relationship_count": 6,
      "average_score": 25.1,
      "strongest_partner": "GB",
      "strongest_score": 30.01,
      "top_partners": [
        {
          "partner": "GB",
          "score": 30.01,
          "band": "low",
          "direct_score": 0.0,
          "similarity_score": 66.7,
          "topic_score": 50.0
        },
        {
          "partner": "UA",
          "score": 29.35,
          "band": "low",
          "direct_score": 6.25,
          "similarity_score": 60.0,
          "topic_score": 41.11
        },
        {
          "partner": "RU",
          "score": 28.71,
          "band": "low",
          "direct_score": 0.0,
          "similarity_score": 65.3,
          "topic_score": 45.58
        },
        {
          "partner": "TR",
          "score": 27.32,
          "band": "low",
          "direct_score": 6.25,
          "similarity_score": 53.3,
          "topic_score": 41.03
        },
        {
          "partner": "CN",
          "score": 20.8,
          "band": "low",
          "direct_score": 0.0,
          "similarity_score": 47.1,
          "topic_score": 33.33
        },
        {
          "partner": "US",
          "score": 14.41,
          "band": "very_low",
          "direct_score": 0.0,
          "similarity_score": 25.8,
          "topic_score": 33.33
        }
      ]
    },
    {
      "country": "GB",
      "relationship_count": 14,
      "average_score": 22.32,
      "strongest_partner": "LT",
      "strongest_score": 38.32,
      "top_partners": [
        {
          "partner": "LT",
          "score": 38.32,
          "band": "low",
          "direct_score": 0.0,
          "similarity_score": 83.3,
          "topic_score": 66.67
        },
        {
          "partner": "GR",
          "score": 35.98,
          "band": "low",
          "direct_score": 0.0,
          "similarity_score": 86.6,
          "topic_score": 50.0
        },
        {
          "partner": "DE",
          "score": 34.86,
          "band": "low",
          "direct_score": 0.0,
          "similarity_score": 75.3,
          "topic_score": 61.33
        },
        {
          "partner": "FR",
          "score": 30.63,
          "band": "low",
          "direct_score": 12.5,
          "similarity_score": 50.4,
          "topic_score": 46.3
        },
        {
          "partner": "IT",
          "score": 30.01,
          "band": "low",
          "direct_score": 0.0,
          "similarity_score": 66.7,
          "topic_score": 50.0
        },
        {
          "partner": "FI",
          "score": 20.46,
          "band": "low",
          "direct_score": 0.0,
          "similarity_score": 39.3,
          "topic_score": 43.33
        },
        {
          "partner": "HU",
          "score": 19.05,
          "band": "very_low",
          "direct_score": 0.0,
          "similarity_score": 37.1,
          "topic_score": 39.62
        },
        {
          "partner": "SK",
          "score": 18.67,
          "band": "very_low",
          "direct_score": 0.0,
          "similarity_score": 40.0,
          "topic_score": 33.33
        },
        {
          "partner": "IE",
          "score": 18.28,
          "band": "very_low",
          "direct_score": 0.0,
          "similarity_score": 38.7,
          "topic_score": 33.33
        },
        {
          "partner": "PL",
          "score": 18.28,
          "band": "very_low",
          "direct_score": 0.0,
          "similarity_score": 38.7,
          "topic_score": 33.33
        }
      ]
    },
    {
      "country": "US",
      "relationship_count": 13,
      "average_score": 21.58,
      "strongest_partner": "IE",
      "strongest_score": 38.9,
      "top_partners": [
        {
          "partner": "IE",
          "score": 38.9,
          "band": "low",
          "direct_score": 3.12,
          "similarity_score": 80.0,
          "topic_score": 66.67
        },
        {
          "partner": "FI",
          "score": 26.67,
          "band": "low",
          "direct_score": 3.12,
          "similarity_score": 54.8,
          "topic_score": 43.33
        },
        {
          "partner": "FR",
          "score": 25.58,
          "band": "low",
          "direct_score": 3.12,
          "similarity_score": 52.9,
          "topic_score": 40.74
        },
        {
          "partner": "HU",
          "score": 24.87,
          "band": "low",
          "direct_score": 3.12,
          "similarity_score": 51.1,
          "topic_score": 39.89
        },
        {
          "partner": "CZ",
          "score": 20.08,
          "band": "low",
          "direct_score": 0.0,
          "similarity_score": 44.7,
          "topic_score": 33.33
        },
        {
          "partner": "EE",
          "score": 20.08,
          "band": "low",
          "direct_score": 0.0,
          "similarity_score": 44.7,
          "topic_score": 33.33
        },
        {
          "partner": "LV",
          "score": 20.08,
          "band": "low",
          "direct_score": 0.0,
          "similarity_score": 44.7,
          "topic_score": 33.33
        },
        {
          "partner": "SE",
          "score": 20.08,
          "band": "low",
          "direct_score": 0.0,
          "similarity_score": 44.7,
          "topic_score": 33.33
        },
        {
          "partner": "DE",
          "score": 18.84,
          "band": "very_low",
          "direct_score": 0.0,
          "similarity_score": 37.9,
          "topic_score": 37.33
        },
        {
          "partner": "PL",
          "score": 18.67,
          "band": "very_low",
          "direct_score": 0.0,
          "similarity_score": 40.0,
          "topic_score": 33.33
        }
      ]
    }
  ],
  "current": {
    "event_count": 286,
    "graph_event_count": 286
  }
}