{
  "event_count": 231,
  "mode": "all",
  "totals": {
    "for": 916.813,
    "against": 968.924,
    "abstain": 57.262
  },
  "by_country": [
    {
      "country": "BE",
      "for": 40.265,
      "against": 31.144,
      "abstain": 0.63,
      "total": 72.039
    },
    {
      "country": "FR",
      "for": 35.046,
      "against": 34.172,
      "abstain": 2.821,
      "total": 72.039
    },
    {
      "country": "GR",
      "for": 40.131,
      "against": 30.013,
      "abstain": 1.895,
      "total": 72.039
    },
    {
      "country": "IT",
      "for": 32.265,
      "against": 37.731,
      "abstain": 2.043,
      "total": 72.039
    },
    {
      "country": "PT",
      "for": 36.858,
      "against": 33.033,
      "abstain": 2.148,
      "total": 72.039
    },
    {
      "country": "SI",
      "for": 27.036,
      "against": 44.818,
      "abstain": 0.185,
      "total": 72.039
    },
    {
      "country": "SK",
      "for": 46.13,
      "against": 23.168,
      "abstain": 2.741,
      "total": 72.039
    },
    {
      "country": "AT",
      "for": 32.53,
      "against": 36.138,
      "abstain": 3.37,
      "total": 72.038
    },
    {
      "country": "BG",
      "for": 28.772,
      "against": 42.118,
      "abstain": 1.148,
      "total": 72.038
    },
    {
      "country": "CZ",
      "for": 30.383,
      "against": 34.721,
      "abstain": 6.934,
      "total": 72.038
    },
    {
      "country": "DE",
      "for": 27.413,
      "against": 44.625,
      "abstain": 0.0,
      "total": 72.038
    },
    {
      "country": "DK",
      "for": 38.969,
      "against": 32.699,
      "abstain": 0.37,
      "total": 72.038
    },
    {
      "country": "EE",
      "for": 35.154,
      "against": 35.773,
      "abstain": 1.111,
      "total": 72.038
    },
    {
      "country": "ES",
      "for": 29.642,
      "against": 42.396,
      "abstain": 0.0,
      "total": 72.038
    },
    {
      "country": "FI",
      "for": 41.302,
      "against": 30.736,
      "abstain": 0.0,
      "total": 72.038
    },
    {
      "country": "HR",
      "for": 29.672,
      "against": 41.773,
      "abstain": 0.593,
      "total": 72.038
    },
    {
      "country": "HU",
      "for": 25.679,
      "against": 33.684,
      "abstain": 12.675,
      "total": 72.038
    },
    {
      "country": "IE",
      "for": 45.048,
      "against": 24.879,
      "abstain": 2.111,
      "total": 72.038
    },
    {
      "country": "LT",
      "for": 39.598,
      "against": 31.551,
      "abstain": 0.889,
      "total": 72.038
    },
    {
      "country": "LU",
      "for": 26.117,
      "against": 43.551,
      "abstain": 2.37,
      "total": 72.038
    },
    {
      "country": "LV",
      "for": 29.34,
      "against": 42.254,
      "abstain": 0.444,
      "total": 72.038
    },
    {
      "country": "MT",
      "for": 33.672,
      "against": 31.731,
      "abstain": 6.635,
      "total": 72.038
    },
    {
      "country": "NL",
      "for": 32.311,
      "against": 39.32,
      "abstain": 0.407,
      "total": 72.038
    },
    {
      "country": "PL",
      "for": 27.793,
      "against": 43.652,
      "abstain": 0.593,
      "total": 72.038
    },
    {
      "country": "RO",
      "for": 31.635,
      "against": 39.996,
      "abstain": 0.407,
      "total": 72.038
    },
    {
      "country": "SE",
      "for": 34.199,
      "against": 36.728,
      "abstain": 1.111,
      "total": 72.038
    },
    {
      "country": "CY",
      "for": 39.852,
      "against": 26.518,
      "abstain": 3.63,
      "total": 70.0
    }
  ],
  "by_topic": [
    {
      "topic": "trade",
      "for": 656.257,
      "against": 737.072,
      "abstain": 41.669,
      "total": 1434.998
    },
    {
      "topic": "rule_of_law",
      "for": 79.667,
      "against": 93.741,
      "abstain": 2.593,
      "total": 176.001
    },
    {
      "topic": "defence",
      "for": 72.37,
      "against": 44.889,
      "abstain": 4.741,
      "total": 122.0
    },
    {
      "topic": "ukraine_russia",
      "for": 56.778,
      "against": 50.407,
      "abstain": 5.815,
      "total": 113.0
    },
    {
      "topic": "enlargement",
      "for": 27.481,
      "against": 24.741,
      "abstain": 1.778,
      "total": 54.0
    },
    {
      "topic": "fiscal",
      "for": 18.259,
      "against": 12.074,
      "abstain": 0.667,
      "total": 31.0
    },
    {
      "topic": "energy",
      "for": 6.0,
      "against": 6.0,
      "abstain": 0.0,
      "total": 12.0
    }
  ],
  "by_country_topic": [
    {
      "country": "BE",
      "topic": "trade",
      "for": 31.376,
      "against": 21.218,
      "abstain": 0.63,
      "total": 53.224
    },
    {
      "country": "DE",
      "topic": "trade",
      "for": 17.339,
      "against": 35.885,
      "abstain": 0.0,
      "total": 53.224
    },
    {
      "country": "DK",
      "topic": "trade",
      "for": 30.932,
      "against": 22.107,
      "abstain": 0.185,
      "total": 53.224
    },
    {
      "country": "EE",
      "topic": "trade",
      "for": 25.265,
      "against": 26.848,
      "abstain": 1.111,
      "total": 53.224
    },
    {
      "country": "ES",
      "topic": "trade",
      "for": 17.791,
      "against": 35.433,
      "abstain": 0.0,
      "total": 53.224
    },
    {
      "country": "GR",
      "topic": "trade",
      "for": 28.65,
      "against": 23.568,
      "abstain": 1.006,
      "total": 53.224
    },
    {
      "country": "HU",
      "topic": "trade",
      "for": 18.494,
      "against": 23.61,
      "abstain": 11.12,
      "total": 53.224
    },
    {
      "country": "IE",
      "topic": "trade",
      "for": 35.382,
      "against": 17.101,
      "abstain": 0.741,
      "total": 53.224
    },
    {
      "country": "IT",
      "topic": "trade",
      "for": 23.006,
      "against": 29.323,
      "abstain": 0.895,
      "total": 53.224
    },
    {
      "country": "LT",
      "topic": "trade",
      "for": 27.932,
      "against": 24.403,
      "abstain": 0.889,
      "total": 53.224
    },
    {
      "country": "PL",
      "topic": "trade",
      "for": 16.83,
      "against": 35.801,
      "abstain": 0.593,
      "total": 53.224
    },
    {
      "country": "PT",
      "topic": "trade",
      "for": 28.895,
      "against": 22.181,
      "abstain": 2.148,
      "total": 53.224
    },
    {
      "country": "SI",
      "topic": "trade",
      "for": 14.999,
      "against": 38.04,
      "abstain": 0.185,
      "total": 53.224
    },
    {
      "country": "SK",
      "topic": "trade",
      "for": 38.574,
      "against": 12.65,
      "abstain": 2.0,
      "total": 53.224
    },
    {
      "country": "AT",
      "topic": "trade",
      "for": 22.604,
      "against": 28.138,
      "abstain": 2.481,
      "total": 53.223
    },
    {
      "country": "BG",
      "topic": "trade",
      "for": 17.809,
      "against": 34.266,
      "abstain": 1.148,
      "total": 53.223
    },
    {
      "country": "CZ",
      "topic": "trade",
      "for": 21.531,
      "against": 27.832,
      "abstain": 3.86,
      "total": 53.223
    },
    {
      "country": "FI",
      "topic": "trade",
      "for": 31.672,
      "against": 21.551,
      "abstain": 0.0,
      "total": 53.223
    },
    {
      "country": "FR",
      "topic": "trade",
      "for": 26.638,
      "against": 24.839,
      "abstain": 1.746,
      "total": 53.223
    },
    {
      "country": "HR",
      "topic": "trade",
      "for": 18.524,
      "against": 34.44,
      "abstain": 0.259,
      "total": 53.223
    },
    {
      "country": "LU",
      "topic": "trade",
      "for": 17.561,
      "against": 33.477,
      "abstain": 2.185,
      "total": 53.223
    },
    {
      "country": "LV",
      "topic": "trade",
      "for": 16.563,
      "against": 36.216,
      "abstain": 0.444,
      "total": 53.223
    },
    {
      "country": "MT",
      "topic": "trade",
      "for": 30.783,
      "against": 18.249,
      "abstain": 4.191,
      "total": 53.223
    },
    {
      "country": "NL",
      "topic": "trade",
      "for": 23.125,
      "against": 29.691,
      "abstain": 0.407,
      "total": 53.223
    },
    {
      "country": "RO",
      "topic": "trade",
      "for": 19.302,
      "against": 33.514,
      "abstain": 0.407,
      "total": 53.223
    },
    {
      "country": "SE",
      "topic": "trade",
      "for": 24.866,
      "against": 27.246,
      "abstain": 1.111,
      "total": 53.223
    },
    {
      "country": "CY",
      "topic": "trade",
      "for": 29.815,
      "against": 19.444,
      "abstain": 1.926,
      "total": 51.185
    },
    {
      "country": "AT",
      "topic": "rule_of_law",
      "for": 2.519,
      "against": 4.0,
      "abstain": 0.0,
      "total": 6.519
    },
    {
      "country": "BE",
      "topic": "rule_of_law",
      "for": 3.0,
      "against": 3.519,
      "abstain": 0.0,
      "total": 6.519
    },
    {
      "country": "CZ",
      "topic": "rule_of_law",
      "for": 3.778,
      "against": 2.037,
      "abstain": 0.704,
      "total": 6.519
    },
    {
      "country": "DK",
      "topic": "rule_of_law",
      "for": 1.63,
      "against": 4.704,
      "abstain": 0.185,
      "total": 6.519
    },
    {
      "country": "EE",
      "topic": "rule_of_law",
      "for": 2.63,
      "against": 3.889,
      "abstain": 0.0,
      "total": 6.519
    },
    {
      "country": "FR",
      "topic": "rule_of_law",
      "for": 3.519,
      "against": 3.0,
      "abstain": 0.0,
      "total": 6.519
    },
    {
      "country": "GR",
      "topic": "rule_of_law",
      "for": 4.63,
      "against": 1.889,
      "abstain": 0.0,
      "total": 6.519
    },
    {
      "country": "HU",
      "topic": "rule_of_law",
      "for": 3.667,
      "against": 2.63,
      "abstain": 0.222,
      "total": 6.519
    },
    {
      "country": "IE",
      "topic": "rule_of_law",
      "for": 3.0,
      "against": 3.519,
      "abstain": 0.0,
      "total": 6.519
    },
    {
      "country": "IT",
      "topic": "rule_of_law",
      "for": 2.815,
      "against": 3.704,
      "abstain": 0.0,
      "total": 6.519
    },
    {
      "country": "BG",
      "topic": "rule_of_law",
      "for": 3.074,
      "against": 3.444,
      "abstain": 0.0,
      "total": 6.518
    },
    {
      "country": "CY",
      "topic": "rule_of_law",
      "for": 3.37,
      "against": 2.333,
      "abstain": 0.815,
      "total": 6.518
    },
    {
      "country": "DE",
      "topic": "rule_of_law",
      "for": 2.259,
      "against": 4.259,
      "abstain": 0.0,
      "total": 6.518
    },
    {
      "country": "ES",
      "topic": "rule_of_law",
      "for": 3.37,
      "against": 3.148,
      "abstain": 0.0,
      "total": 6.518
    },
    {
      "country": "FI",
      "topic": "rule_of_law",
      "for": 2.444,
      "against": 4.074,
      "abstain": 0.0,
      "total": 6.518
    },
    {
      "country": "HR",
      "topic": "rule_of_law",
      "for": 3.407,
      "against": 3.111,
      "abstain": 0.0,
      "total": 6.518
    },
    {
      "country": "LT",
      "topic": "rule_of_law",
      "for": 3.037,
      "against": 3.481,
      "abstain": 0.0,
      "total": 6.518
    },
    {
      "country": "LU",
      "topic": "rule_of_law",
      "for": 2.444,
      "against": 3.889,
      "abstain": 0.185,
      "total": 6.518
    },
    {
      "country": "LV",
      "topic": "rule_of_law",
      "for": 3.296,
      "against": 3.222,
      "abstain": 0.0,
      "total": 6.518
    },
    {
      "country": "MT",
      "topic": "rule_of_law",
      "for": 0.815,
      "against": 5.481,
      "abstain": 0.222,
      "total": 6.518
    },
    {
      "country": "NL",
      "topic": "rule_of_law",
      "for": 2.259,
      "against": 4.259,
      "abstain": 0.0,
      "total": 6.518
    },
    {
      "country": "PL",
      "topic": "rule_of_law",
      "for": 3.444,
      "against": 3.074,
      "abstain": 0.0,
      "total": 6.518
    },
    {
      "country": "PT",
      "topic": "rule_of_law",
      "for": 2.37,
      "against": 4.148,
      "abstain": 0.0,
      "total": 6.518
    },
    {
      "country": "RO",
      "topic": "rule_of_law",
      "for": 3.222,
      "against": 3.296,
      "abstain": 0.0,
      "total": 6.518
    },
    {
      "country": "SE",
      "topic": "rule_of_law",
      "for": 2.074,
      "against": 4.444,
      "abstain": 0.0,
      "total": 6.518
    },
    {
      "country": "SI",
      "topic": "rule_of_law",
      "for": 3.444,
      "against": 3.074,
      "abstain": 0.0,
      "total": 6.518
    },
    {
      "country": "SK",
      "topic": "rule_of_law",
      "for": 4.148,
      "against": 2.111,
      "abstain": 0.259,
      "total": 6.518
    },
    {
      "country": "AT",
      "topic": "defence",
      "for": 3.926,
      "against": 0.593,
      "abstain": 0.0,
      "total": 4.519
    },
    {
      "country": "BG",
      "topic": "defence",
      "for": 3.852,
      "against": 0.667,
      "abstain": 0.0,
      "total": 4.519
    },
    {
      "country": "CY",
      "topic": "defence",
      "for": 2.333,
      "against": 1.667,
      "abstain": 0.519,
      "total": 4.519
    },
    {
      "country": "DK",
      "topic": "defence",
      "for": 3.0,
      "against": 1.519,
      "abstain": 0.0,
      "total": 4.519
    },
    {
      "country": "EE",
      "topic": "defence",
      "for": 3.0,
      "against": 1.519,
      "abstain": 0.0,
      "total": 4.519
    },
    {
      "country": "ES",
      "topic": "defence",
      "for": 3.852,
      "against": 0.667,
      "abstain": 0.0,
      "total": 4.519
    },
    {
      "country": "FI",
      "topic": "defence",
      "for": 2.63,
      "against": 1.889,
      "abstain": 0.0,
      "total": 4.519
    },
    {
      "country": "FR",
      "topic": "defence",
      "for": 0.889,
      "against": 3.037,
      "abstain": 0.593,
      "total": 4.519
    },
    {
      "country": "GR",
      "topic": "defence",
      "for": 2.593,
      "against": 1.704,
      "abstain": 0.222,
      "total": 4.519
    },
    {
      "country": "HU",
      "topic": "defence",
      "for": 1.667,
      "against": 2.333,
      "abstain": 0.519,
      "total": 4.519
    },
    {
      "country": "IE",
      "topic": "defence",
      "for": 1.778,
      "against": 1.63,
      "abstain": 1.111,
      "total": 4.519
    },
    {
      "country": "LT",
      "topic": "defence",
      "for": 3.852,
      "against": 0.667,
      "abstain": 0.0,
      "total": 4.519
    },
    {
      "country": "LV",
      "topic": "defence",
      "for": 3.519,
      "against": 1.0,
      "abstain": 0.0,
      "total": 4.519
    },
    {
      "country": "MT",
      "topic": "defence",
      "for": 0.667,
      "against": 2.815,
      "abstain": 1.037,
      "total": 4.519
    },
    {
      "country": "NL",
      "topic": "defence",
      "for": 2.63,
      "against": 1.889,
      "abstain": 0.0,
      "total": 4.519
    },
    {
      "country": "PL",
      "topic": "defence",
      "for": 2.889,
      "against": 1.63,
      "abstain": 0.0,
      "total": 4.519
    },
    {
      "country": "RO",
      "topic": "defence",
      "for": 3.852,
      "against": 0.667,
      "abstain": 0.0,
      "total": 4.519
    },
    {
      "country": "SE",
      "topic": "defence",
      "for": 2.667,
      "against": 1.852,
      "abstain": 0.0,
      "total": 4.519
    },
    {
      "country": "SI",
      "topic": "defence",
      "for": 3.852,
      "against": 0.667,
      "abstain": 0.0,
      "total": 4.519
    },
    {
      "country": "BE",
      "topic": "defence",
      "for": 2.259,
      "against": 2.259,
      "abstain": 0.0,
      "total": 4.518
    },
    {
      "country": "CZ",
      "topic": "defence",
      "for": 1.593,
      "against": 2.444,
      "abstain": 0.481,
      "total": 4.518
    },
    {
      "country": "DE",
      "topic": "defence",
      "for": 3.481,
      "against": 1.037,
      "abstain": 0.0,
      "total": 4.518
    },
    {
      "country": "HR",
      "topic": "defence",
      "for": 3.444,
      "against": 1.074,
      "abstain": 0.0,
      "total": 4.518
    },
    {
      "country": "IT",
      "topic": "defence",
      "for": 2.296,
      "against": 1.963,
      "abstain": 0.259,
      "total": 4.518
    },
    {
      "country": "LU",
      "topic": "defence",
      "for": 2.259,
      "against": 2.259,
      "abstain": 0.0,
      "total": 4.518
    },
    {
      "country": "PT",
      "topic": "defence",
      "for": 2.481,
      "against": 2.037,
      "abstain": 0.0,
      "total": 4.518
    },
    {
      "country": "SK",
      "topic": "defence",
      "for": 1.111,
      "against": 3.407,
      "abstain": 0.0,
      "total": 4.518
    },
    {
      "country": "BG",
      "topic": "ukraine_russia",
      "for": 1.593,
      "against": 2.593,
      "abstain": 0.0,
      "total": 4.186
    },
    {
      "country": "GR",
      "topic": "ukraine_russia",
      "for": 2.704,
      "against": 0.815,
      "abstain": 0.667,
      "total": 4.186
    },
    {
      "country": "LT",
      "topic": "ukraine_russia",
      "for": 1.593,
      "against": 2.593,
      "abstain": 0.0,
      "total": 4.186
    },
    {
      "country": "AT",
      "topic": "ukraine_russia",
      "for": 1.741,
      "against": 2.0,
      "abstain": 0.444,
      "total": 4.185
    },
    {
      "country": "BE",
      "topic": "ukraine_russia",
      "for": 2.074,
      "against": 2.111,
      "abstain": 0.0,
      "total": 4.185
    },
    {
      "country": "CY",
      "topic": "ukraine_russia",
      "for": 3.148,
      "against": 0.667,
      "abstain": 0.37,
      "total": 4.185
    },
    {
      "country": "CZ",
      "topic": "ukraine_russia",
      "for": 1.185,
      "against": 1.444,
      "abstain": 1.556,
      "total": 4.185
    },
    {
      "country": "DE",
      "topic": "ukraine_russia",
      "for": 2.074,
      "against": 2.111,
      "abstain": 0.0,
      "total": 4.185
    },
    {
      "country": "DK",
      "topic": "ukraine_russia",
      "for": 1.852,
      "against": 2.333,
      "abstain": 0.0,
      "total": 4.185
    },
    {
      "country": "EE",
      "topic": "ukraine_russia",
      "for": 1.815,
      "against": 2.37,
      "abstain": 0.0,
      "total": 4.185
    },
    {
      "country": "ES",
      "topic": "ukraine_russia",
      "for": 2.852,
      "against": 1.333,
      "abstain": 0.0,
      "total": 4.185
    },
    {
      "country": "FI",
      "topic": "ukraine_russia",
      "for": 2.074,
      "against": 2.111,
      "abstain": 0.0,
      "total": 4.185
    },
    {
      "country": "HR",
      "topic": "ukraine_russia",
      "for": 3.111,
      "against": 1.074,
      "abstain": 0.0,
      "total": 4.185
    },
    {
      "country": "HU",
      "topic": "ukraine_russia",
      "for": 1.148,
      "against": 2.63,
      "abstain": 0.407,
      "total": 4.185
    },
    {
      "country": "IE",
      "topic": "ukraine_russia",
      "for": 2.667,
      "against": 1.259,
      "abstain": 0.259,
      "total": 4.185
    },
    {
      "country": "LU",
      "topic": "ukraine_russia",
      "for": 1.815,
      "against": 2.37,
      "abstain": 0.0,
      "total": 4.185
    },
    {
      "country": "LV",
      "topic": "ukraine_russia",
      "for": 2.815,
      "against": 1.37,
      "abstain": 0.0,
      "total": 4.185
    },
    {
      "country": "MT",
      "topic": "ukraine_russia",
      "for": 1.185,
      "against": 2.148,
      "abstain": 0.852,
      "total": 4.185
    },
    {
      "country": "NL",
      "topic": "ukraine_russia",
      "for": 2.074,
      "against": 2.111,
      "abstain": 0.0,
      "total": 4.185
    },
    {
      "country": "PL",
      "topic": "ukraine_russia",
      "for": 2.185,
      "against": 2.0,
      "abstain": 0.0,
      "total": 4.185
    },
    {
      "country": "PT",
      "topic": "ukraine_russia",
      "for": 1.815,
      "against": 2.37,
      "abstain": 0.0,
      "total": 4.185
    },
    {
      "country": "RO",
      "topic": "ukraine_russia",
      "for": 2.333,
      "against": 1.852,
      "abstain": 0.0,
      "total": 4.185
    },
    {
      "country": "SE",
      "topic": "ukraine_russia",
      "for": 2.074,
      "against": 2.111,
      "abstain": 0.0,
      "total": 4.185
    },
    {
      "country": "SI",
      "topic": "ukraine_russia",
      "for": 2.296,
      "against": 1.889,
      "abstain": 0.0,
      "total": 4.185
    },
    {
      "country": "SK",
      "topic": "ukraine_russia",
      "for": 1.63,
      "against": 2.074,
      "abstain": 0.481,
      "total": 4.185
    },
    {
      "country": "FR",
      "topic": "ukraine_russia",
      "for": 2.444,
      "against": 1.259,
      "abstain": 0.481,
      "total": 4.184
    },
    {
      "country": "IT",
      "topic": "ukraine_russia",
      "for": 2.481,
      "against": 1.407,
      "abstain": 0.296,
      "total": 4.184
    },
    {
      "country": "AT",
      "topic": "enlargement",
      "for": 0.815,
      "against": 0.741,
      "abstain": 0.444,
      "total": 2.0
    },
    {
      "country": "BE",
      "topic": "enlargement",
      "for": 1.074,
      "against": 0.926,
      "abstain": 0.0,
      "total": 2.0
    },
    {
      "country": "BG",
      "topic": "enlargement",
      "for": 1.259,
      "against": 0.741,
      "abstain": 0.0,
      "total": 2.0
    },
    {
      "country": "CY",
      "topic": "enlargement",
      "for": 0.0,
      "against": 2.0,
      "abstain": 0.0,
      "total": 2.0
    },
    {
      "country": "CZ",
      "topic": "enlargement",
      "for": 0.926,
      "against": 0.741,
      "abstain": 0.333,
      "total": 2.0
    },
    {
      "country": "DE",
      "topic": "enlargement",
      "for": 1.074,
      "against": 0.926,
      "abstain": 0.0,
      "total": 2.0
    },
    {
      "country": "DK",
      "topic": "enlargement",
      "for": 1.074,
      "against": 0.926,
      "abstain": 0.0,
      "total": 2.0
    },
    {
      "country": "EE",
      "topic": "enlargement",
      "for": 1.259,
      "against": 0.741,
      "abstain": 0.0,
      "total": 2.0
    },
    {
      "country": "ES",
      "topic": "enlargement",
      "for": 0.815,
      "against": 1.185,
      "abstain": 0.0,
      "total": 2.0
    },
    {
      "country": "FI",
      "topic": "enlargement",
      "for": 2.0,
      "against": 0.0,
      "abstain": 0.0,
      "total": 2.0
    },
    {
      "country": "FR",
      "topic": "enlargement",
      "for": 0.444,
      "against": 1.556,
      "abstain": 0.0,
      "total": 2.0
    },
    {
      "country": "GR",
      "topic": "enlargement",
      "for": 0.444,
      "against": 1.556,
      "abstain": 0.0,
      "total": 2.0
    },
    {
      "country": "HR",
      "topic": "enlargement",
      "for": 0.0,
      "against": 1.667,
      "abstain": 0.333,
      "total": 2.0
    },
    {
      "country": "HU",
      "topic": "enlargement",
      "for": 0.0,
      "against": 2.0,
      "abstain": 0.0,
      "total": 2.0
    },
    {
      "country": "IE",
      "topic": "enlargement",
      "for": 1.741,
      "against": 0.259,
      "abstain": 0.0,
      "total": 2.0
    },
    {
      "country": "IT",
      "topic": "enlargement",
      "for": 0.741,
      "against": 0.926,
      "abstain": 0.333,
      "total": 2.0
    },
    {
      "country": "LT",
      "topic": "enlargement",
      "for": 2.0,
      "against": 0.0,
      "abstain": 0.0,
      "total": 2.0
    },
    {
      "country": "LU",
      "topic": "enlargement",
      "for": 1.259,
      "against": 0.741,
      "abstain": 0.0,
      "total": 2.0
    },
    {
      "country": "LV",
      "topic": "enlargement",
      "for": 1.741,
      "against": 0.259,
      "abstain": 0.0,
      "total": 2.0
    },
    {
      "country": "MT",
      "topic": "enlargement",
      "for": 0.0,
      "against": 1.667,
      "abstain": 0.333,
      "total": 2.0
    },
    {
      "country": "NL",
      "topic": "enlargement",
      "for": 1.741,
      "against": 0.259,
      "abstain": 0.0,
      "total": 2.0
    },
    {
      "country": "PL",
      "topic": "enlargement",
      "for": 1.259,
      "against": 0.741,
      "abstain": 0.0,
      "total": 2.0
    },
    {
      "country": "PT",
      "topic": "enlargement",
      "for": 1.074,
      "against": 0.926,
      "abstain": 0.0,
      "total": 2.0
    },
    {
      "country": "RO",
      "topic": "enlargement",
      "for": 1.741,
      "against": 0.259,
      "abstain": 0.0,
      "total": 2.0
    },
    {
      "country": "SE",
      "topic": "enlargement",
      "for": 1.741,
      "against": 0.259,
      "abstain": 0.0,
      "total": 2.0
    },
    {
      "country": "SI",
      "topic": "enlargement",
      "for": 1.259,
      "against": 0.741,
      "abstain": 0.0,
      "total": 2.0
    },
    {
      "country": "SK",
      "topic": "enlargement",
      "for": 0.0,
      "against": 2.0,
      "abstain": 0.0,
      "total": 2.0
    },
    {
      "country": "LU",
      "topic": "fiscal",
      "for": 0.556,
      "against": 0.593,
      "abstain": 0.0,
      "total": 1.149
    },
    {
      "country": "SE",
      "topic": "fiscal",
      "for": 0.556,
      "against": 0.593,
      "abstain": 0.0,
      "total": 1.149
    },
    {
      "country": "AT",
      "topic": "fiscal",
      "for": 0.704,
      "against": 0.444,
      "abstain": 0.0,
      "total": 1.148
    },
    {
      "country": "BE",
      "topic": "fiscal",
      "for": 0.259,
      "against": 0.889,
      "abstain": 0.0,
      "total": 1.148
    },
    {
      "country": "BG",
      "topic": "fiscal",
      "for": 0.963,
      "against": 0.185,
      "abstain": 0.0,
      "total": 1.148
    },
    {
      "country": "CY",
      "topic": "fiscal",
      "for": 0.963,
      "against": 0.185,
      "abstain": 0.0,
      "total": 1.148
    },
    {
      "country": "CZ",
      "topic": "fiscal",
      "for": 1.148,
      "against": 0.0,
      "abstain": 0.0,
      "total": 1.148
    },
    {
      "country": "DE",
      "topic": "fiscal",
      "for": 0.963,
      "against": 0.185,
      "abstain": 0.0,
      "total": 1.148
    },
    {
      "country": "DK",
      "topic": "fiscal",
      "for": 0.259,
      "against": 0.889,
      "abstain": 0.0,
      "total": 1.148
    },
    {
      "country": "EE",
      "topic": "fiscal",
      "for": 0.963,
      "against": 0.185,
      "abstain": 0.0,
      "total": 1.148
    },
    {
      "country": "ES",
      "topic": "fiscal",
      "for": 0.963,
      "against": 0.185,
      "abstain": 0.0,
      "total": 1.148
    },
    {
      "country": "FI",
      "topic": "fiscal",
      "for": 0.259,
      "against": 0.889,
      "abstain": 0.0,
      "total": 1.148
    },
    {
      "country": "FR",
      "topic": "fiscal",
      "for": 0.889,
      "against": 0.259,
      "abstain": 0.0,
      "total": 1.148
    },
    {
      "country": "GR",
      "topic": "fiscal",
      "for": 0.889,
      "against": 0.259,
      "abstain": 0.0,
      "total": 1.148
    },
    {
      "country": "HR",
      "topic": "fiscal",
      "for": 0.963,
      "against": 0.185,
      "abstain": 0.0,
      "total": 1.148
    },
    {
      "country": "IE",
      "topic": "fiscal",
      "for": 0.259,
      "against": 0.889,
      "abstain": 0.0,
      "total": 1.148
    },
    {
      "country": "IT",
      "topic": "fiscal",
      "for": 0.704,
      "against": 0.185,
      "abstain": 0.259,
      "total": 1.148
    },
    {
      "country": "LT",
      "topic": "fiscal",
      "for": 0.963,
      "against": 0.185,
      "abstain": 0.0,
      "total": 1.148
    },
    {
      "country": "LV",
      "topic": "fiscal",
      "for": 0.963,
      "against": 0.185,
      "abstain": 0.0,
      "total": 1.148
    },
    {
      "country": "MT",
      "topic": "fiscal",
      "for": 0.0,
      "against": 1.148,
      "abstain": 0.0,
      "total": 1.148
    },
    {
      "country": "NL",
      "topic": "fiscal",
      "for": 0.259,
      "against": 0.889,
      "abstain": 0.0,
      "total": 1.148
    },
    {
      "country": "PL",
      "topic": "fiscal",
      "for": 0.963,
      "against": 0.185,
      "abstain": 0.0,
      "total": 1.148
    },
    {
      "country": "PT",
      "topic": "fiscal",
      "for": 0.0,
      "against": 1.148,
      "abstain": 0.0,
      "total": 1.148
    },
    {
      "country": "RO",
      "topic": "fiscal",
      "for": 0.963,
      "against": 0.185,
      "abstain": 0.0,
      "total": 1.148
    },
    {
      "country": "SI",
      "topic": "fiscal",
      "for": 0.963,
      "against": 0.185,
      "abstain": 0.0,
      "total": 1.148
    },
    {
      "country": "SK",
      "topic": "fiscal",
      "for": 0.444,
      "against": 0.704,
      "abstain": 0.0,
      "total": 1.148
    },
    {
      "country": "HU",
      "topic": "fiscal",
      "for": 0.481,
      "against": 0.259,
      "abstain": 0.407,
      "total": 1.147
    },
    {
      "country": "AT",
      "topic": "energy",
      "for": 0.222,
      "against": 0.222,
      "abstain": 0.0,
      "total": 0.444
    },
    {
      "country": "BE",
      "topic": "energy",
      "for": 0.222,
      "against": 0.222,
      "abstain": 0.0,
      "total": 0.444
    },
    {
      "country": "BG",
      "topic": "energy",
      "for": 0.222,
      "against": 0.222,
      "abstain": 0.0,
      "total": 0.444
    },
    {
      "country": "CY",
      "topic": "energy",
      "for": 0.222,
      "against": 0.222,
      "abstain": 0.0,
      "total": 0.444
    },
    {
      "country": "CZ",
      "topic": "energy",
      "for": 0.222,
      "against": 0.222,
      "abstain": 0.0,
      "total": 0.444
    },
    {
      "country": "DE",
      "topic": "energy",
      "for": 0.222,
      "against": 0.222,
      "abstain": 0.0,
      "total": 0.444
    },
    {
      "country": "DK",
      "topic": "energy",
      "for": 0.222,
      "against": 0.222,
      "abstain": 0.0,
      "total": 0.444
    },
    {
      "country": "EE",
      "topic": "energy",
      "for": 0.222,
      "against": 0.222,
      "abstain": 0.0,
      "total": 0.444
    },
    {
      "country": "ES",
      "topic": "energy",
      "for": 0.0,
      "against": 0.444,
      "abstain": 0.0,
      "total": 0.444
    },
    {
      "country": "FI",
      "topic": "energy",
      "for": 0.222,
      "against": 0.222,
      "abstain": 0.0,
      "total": 0.444
    },
    {
      "country": "FR",
      "topic": "energy",
      "for": 0.222,
      "against": 0.222,
      "abstain": 0.0,
      "total": 0.444
    },
    {
      "country": "GR",
      "topic": "energy",
      "for": 0.222,
      "against": 0.222,
      "abstain": 0.0,
      "total": 0.444
    },
    {
      "country": "HR",
      "topic": "energy",
      "for": 0.222,
      "against": 0.222,
      "abstain": 0.0,
      "total": 0.444
    },
    {
      "country": "HU",
      "topic": "energy",
      "for": 0.222,
      "against": 0.222,
      "abstain": 0.0,
      "total": 0.444
    },
    {
      "country": "IE",
      "topic": "energy",
      "for": 0.222,
      "against": 0.222,
      "abstain": 0.0,
      "total": 0.444
    },
    {
      "country": "IT",
      "topic": "energy",
      "for": 0.222,
      "against": 0.222,
      "abstain": 0.0,
      "total": 0.444
    },
    {
      "country": "LT",
      "topic": "energy",
      "for": 0.222,
      "against": 0.222,
      "abstain": 0.0,
      "total": 0.444
    },
    {
      "country": "LU",
      "topic": "energy",
      "for": 0.222,
      "against": 0.222,
      "abstain": 0.0,
      "total": 0.444
    },
    {
      "country": "LV",
      "topic": "energy",
      "for": 0.444,
      "against": 0.0,
      "abstain": 0.0,
      "total": 0.444
    },
    {
      "country": "MT",
      "topic": "energy",
      "for": 0.222,
      "against": 0.222,
      "abstain": 0.0,
      "total": 0.444
    },
    {
      "country": "NL",
      "topic": "energy",
      "for": 0.222,
      "against": 0.222,
      "abstain": 0.0,
      "total": 0.444
    },
    {
      "country": "PL",
      "topic": "energy",
      "for": 0.222,
      "against": 0.222,
      "abstain": 0.0,
      "total": 0.444
    },
    {
      "country": "PT",
      "topic": "energy",
      "for": 0.222,
      "against": 0.222,
      "abstain": 0.0,
      "total": 0.444
    },
    {
      "country": "RO",
      "topic": "energy",
      "for": 0.222,
      "against": 0.222,
      "abstain": 0.0,
      "total": 0.444
    },
    {
      "country": "SE",
      "topic": "energy",
      "for": 0.222,
      "against": 0.222,
      "abstain": 0.0,
      "total": 0.444
    },
    {
      "country": "SI",
      "topic": "energy",
      "for": 0.222,
      "against": 0.222,
      "abstain": 0.0,
      "total": 0.444
    },
    {
      "country": "SK",
      "topic": "energy",
      "for": 0.222,
      "against": 0.222,
      "abstain": 0.0,
      "total": 0.444
    }
  ]
}