{
  "topics": [
    "migration",
    "ukraine_russia",
    "enlargement",
    "defence",
    "energy",
    "fiscal",
    "rule_of_law",
    "trade"
  ],
  "rows": [
    {
      "country": "AT",
      "migration": 0.0,
      "ukraine_russia": 1.0,
      "enlargement": 0.0,
      "defence": 0.0,
      "energy": 0.0,
      "fiscal": 0.0,
      "rule_of_law": 0.0,
      "trade": 0.0,
      "total": 1.0
    },
    {
      "country": "BE",
      "migration": 0.0,
      "ukraine_russia": 0.47619,
      "enlargement": 0.0,
      "defence": 0.119048,
      "energy": 0.404762,
      "fiscal": 0.0,
      "rule_of_law": 0.0,
      "trade": 0.0,
      "total": 1.0
    },
    {
      "country": "DE",
      "migration": 0.666667,
      "ukraine_russia": 0.333333,
      "enlargement": 0.0,
      "defence": 0.0,
      "energy": 0.0,
      "fiscal": 0.0,
      "rule_of_law": 0.0,
      "trade": 0.0,
      "total": 1.0
    },
    {
      "country": "ES",
      "migration": 0.0,
      "ukraine_russia": 0.333333,
      "enlargement": 0.0,
      "defence": 0.333333,
      "energy": 0.333333,
      "fiscal": 0.0,
      "rule_of_law": 0.0,
      "trade": 0.0,
      "total": 1.0
    },
    {
      "country": "FR",
      "migration": 0.0,
      "ukraine_russia": 0.263158,
      "enlargement": 0.0,
      "defence": 0.263158,
      "energy": 0.473684,
      "fiscal": 0.0,
      "rule_of_law": 0.0,
      "trade": 0.0,
      "total": 1.0
    },
    {
      "country": "GB",
      "migration": 0.137931,
      "ukraine_russia": 0.448276,
      "enlargement": 0.0,
      "defence": 0.206897,
      "energy": 0.206897,
      "fiscal": 0.0,
      "rule_of_law": 0.0,
      "trade": 0.0,
      "total": 1.0
    },
    {
      "country": "HU",
      "migration": 0.0,
      "ukraine_russia": 0.549505,
      "enlargement": 0.0,
      "defence": 0.128713,
      "energy": 0.242574,
      "fiscal": 0.0,
      "rule_of_law": 0.079208,
      "trade": 0.0,
      "total": 1.0
    },
    {
      "country": "IE",
      "migration": 0.0,
      "ukraine_russia": 0.5,
      "enlargement": 0.0,
      "defence": 0.5,
      "energy": 0.0,
      "fiscal": 0.0,
      "rule_of_law": 0.0,
      "trade": 0.0,
      "total": 1.0
    },
    {
      "country": "IT",
      "migration": 0.0,
      "ukraine_russia": 0.5,
      "enlargement": 0.0,
      "defence": 0.0,
      "energy": 0.5,
      "fiscal": 0.0,
      "rule_of_law": 0.0,
      "trade": 0.0,
      "total": 1.0
    },
    {
      "country": "MT",
      "migration": 0.0,
      "ukraine_russia": 0.5,
      "enlargement": 0.0,
      "defence": 0.0,
      "energy": 0.5,
      "fiscal": 0.0,
      "rule_of_law": 0.0,
      "trade": 0.0,
      "total": 1.0
    },
    {
      "country": "NL",
      "migration": 0.0,
      "ukraine_russia": 1.0,
      "enlargement": 0.0,
      "defence": 0.0,
      "energy": 0.0,
      "fiscal": 0.0,
      "rule_of_law": 0.0,
      "trade": 0.0,
      "total": 1.0
    },
    {
      "country": "PL",
      "migration": 0.142857,
      "ukraine_russia": 0.571429,
      "enlargement": 0.0,
      "defence": 0.142857,
      "energy": 0.142857,
      "fiscal": 0.0,
      "rule_of_law": 0.0,
      "trade": 0.0,
      "total": 1.0
    },
    {
      "country": "RU",
      "migration": 0.018018,
      "ukraine_russia": 0.603604,
      "enlargement": 0.0,
      "defence": 0.067568,
      "energy": 0.265766,
      "fiscal": 0.0,
      "rule_of_law": 0.045045,
      "trade": 0.0,
      "total": 1.0
    },
    {
      "country": "SE",
      "migration": 0.0,
      "ukraine_russia": 0.142857,
      "enlargement": 0.0,
      "defence": 0.0,
      "energy": 0.0,
      "fiscal": 0.0,
      "rule_of_law": 0.857143,
      "trade": 0.0,
      "total": 1.0
    },
    {
      "country": "SI",
      "migration": 0.0,
      "ukraine_russia": 0.333333,
      "enlargement": 0.0,
      "defence": 0.0,
      "energy": 0.333333,
      "fiscal": 0.0,
      "rule_of_law": 0.0,
      "trade": 0.333333,
      "total": 1.0
    },
    {
      "country": "SK",
      "migration": 0.0,
      "ukraine_russia": 0.789474,
      "enlargement": 0.0,
      "defence": 0.052632,
      "energy": 0.157895,
      "fiscal": 0.0,
      "rule_of_law": 0.0,
      "trade": 0.0,
      "total": 1.0
    },
    {
      "country": "TR",
      "migration": 0.4,
      "ukraine_russia": 0.0,
      "enlargement": 0.0,
      "defence": 0.0,
      "energy": 0.0,
      "fiscal": 0.0,
      "rule_of_law": 0.6,
      "trade": 0.0,
      "total": 1.0
    },
    {
      "country": "UA",
      "migration": 0.017021,
      "ukraine_russia": 0.489362,
      "enlargement": 0.0,
      "defence": 0.148936,
      "energy": 0.310638,
      "fiscal": 0.0,
      "rule_of_law": 0.0,
      "trade": 0.034043,
      "total": 1.0
    },
    {
      "country": "US",
      "migration": 0.0,
      "ukraine_russia": 0.125,
      "enlargement": 0.0,
      "defence": 0.125,
      "energy": 0.375,
      "fiscal": 0.0,
      "rule_of_law": 0.375,
      "trade": 0.0,
      "total": 1.0
    }
  ],
  "event_count": 718,
  "mode": "external",
  "normalized": true
}