{
  "topics": [
    "migration",
    "ukraine_russia",
    "enlargement",
    "defence",
    "energy",
    "fiscal",
    "rule_of_law",
    "trade"
  ],
  "rows": [
    {
      "country": "AT",
      "migration": 0.0,
      "ukraine_russia": 11.0,
      "enlargement": 0.0,
      "defence": 26.22,
      "energy": 1.0,
      "fiscal": 11.6,
      "rule_of_law": 4.0,
      "trade": 44.3,
      "total": 98.12
    },
    {
      "country": "BE",
      "migration": 0.0,
      "ukraine_russia": 20.0,
      "enlargement": 0.0,
      "defence": 129.5,
      "energy": 20.0,
      "fiscal": 0.0,
      "rule_of_law": 22.9,
      "trade": 50.75,
      "total": 243.15
    },
    {
      "country": "BG",
      "migration": 0.0,
      "ukraine_russia": 1.0,
      "enlargement": 0.0,
      "defence": 55.86,
      "energy": 0.0,
      "fiscal": 0.0,
      "rule_of_law": 13.54,
      "trade": 5.99,
      "total": 76.39
    },
    {
      "country": "CN",
      "migration": 0.0,
      "ukraine_russia": 57.0,
      "enlargement": 0.0,
      "defence": 184.86,
      "energy": 4.0,
      "fiscal": 0.0,
      "rule_of_law": 0.0,
      "trade": 34.77,
      "total": 280.63
    },
    {
      "country": "CY",
      "migration": 1.0,
      "ukraine_russia": 24.6,
      "enlargement": 0.0,
      "defence": 144.51,
      "energy": 4.0,
      "fiscal": 0.0,
      "rule_of_law": 13.0,
      "trade": 0.0,
      "total": 187.11
    },
    {
      "country": "CZ",
      "migration": 0.0,
      "ukraine_russia": 21.0,
      "enlargement": 0.0,
      "defence": 35.38,
      "energy": 0.0,
      "fiscal": 0.0,
      "rule_of_law": 0.0,
      "trade": 23.6,
      "total": 79.98
    },
    {
      "country": "DE",
      "migration": 11.0,
      "ukraine_russia": 30.4,
      "enlargement": 0.0,
      "defence": 529.35,
      "energy": 28.0,
      "fiscal": 16.3,
      "rule_of_law": 71.06,
      "trade": 131.17,
      "total": 817.28
    },
    {
      "country": "DK",
      "migration": 1.0,
      "ukraine_russia": 22.0,
      "enlargement": 0.0,
      "defence": 52.52,
      "energy": 2.0,
      "fiscal": 6.2,
      "rule_of_law": 12.0,
      "trade": 27.42,
      "total": 123.14
    },
    {
      "country": "EE",
      "migration": 0.0,
      "ukraine_russia": 4.0,
      "enlargement": 0.0,
      "defence": 38.4,
      "energy": 0.0,
      "fiscal": 0.0,
      "rule_of_law": 25.7,
      "trade": 21.78,
      "total": 89.88
    },
    {
      "country": "ES",
      "migration": 0.0,
      "ukraine_russia": 9.7,
      "enlargement": 0.0,
      "defence": 391.0,
      "energy": 22.0,
      "fiscal": 35.4,
      "rule_of_law": 82.04,
      "trade": 97.38,
      "total": 637.52
    },
    {
      "country": "FI",
      "migration": 0.0,
      "ukraine_russia": 13.0,
      "enlargement": 0.0,
      "defence": 41.44,
      "energy": 2.0,
      "fiscal": 0.0,
      "rule_of_law": 17.88,
      "trade": 28.08,
      "total": 102.4
    },
    {
      "country": "FR",
      "migration": 22.0,
      "ukraine_russia": 121.65,
      "enlargement": 1.0,
      "defence": 709.79,
      "energy": 46.0,
      "fiscal": 23.0,
      "rule_of_law": 114.71,
      "trade": 161.8,
      "total": 1199.95
    },
    {
      "country": "GB",
      "migration": 21.0,
      "ukraine_russia": 79.5,
      "enlargement": 0.0,
      "defence": 589.01,
      "energy": 16.0,
      "fiscal": 5.6,
      "rule_of_law": 114.3,
      "trade": 84.84,
      "total": 910.25
    },
    {
      "country": "GR",
      "migration": 6.0,
      "ukraine_russia": 23.7,
      "enlargement": 0.0,
      "defence": 79.2,
      "energy": 2.0,
      "fiscal": 0.0,
      "rule_of_law": 3.72,
      "trade": 25.09,
      "total": 139.71
    },
    {
      "country": "HR",
      "migration": 0.0,
      "ukraine_russia": 4.0,
      "enlargement": 0.0,
      "defence": 0.0,
      "energy": 4.0,
      "fiscal": 0.0,
      "rule_of_law": 1.0,
      "trade": 7.2,
      "total": 16.2
    },
    {
      "country": "HU",
      "migration": 2.0,
      "ukraine_russia": 212.0,
      "enlargement": 0.0,
      "defence": 67.03,
      "energy": 75.0,
      "fiscal": 7.0,
      "rule_of_law": 42.14,
      "trade": 34.14,
      "total": 439.31
    },
    {
      "country": "IE",
      "migration": 0.0,
      "ukraine_russia": 49.4,
      "enlargement": 0.0,
      "defence": 385.56,
      "energy": 6.0,
      "fiscal": 3.6,
      "rule_of_law": 73.73,
      "trade": 109.16,
      "total": 627.45
    },
    {
      "country": "IT",
      "migration": 6.0,
      "ukraine_russia": 28.9,
      "enlargement": 0.0,
      "defence": 306.04,
      "energy": 14.0,
      "fiscal": 20.8,
      "rule_of_law": 42.76,
      "trade": 72.86,
      "total": 491.36
    },
    {
      "country": "LT",
      "migration": 5.0,
      "ukraine_russia": 5.0,
      "enlargement": 0.0,
      "defence": 4.1,
      "energy": 5.0,
      "fiscal": 0.0,
      "rule_of_law": 0.0,
      "trade": 4.84,
      "total": 23.94
    },
    {
      "country": "LV",
      "migration": 0.0,
      "ukraine_russia": 5.0,
      "enlargement": 0.0,
      "defence": 8.2,
      "energy": 0.0,
      "fiscal": 0.0,
      "rule_of_law": 0.0,
      "trade": 35.54,
      "total": 48.74
    },
    {
      "country": "MT",
      "migration": 0.0,
      "ukraine_russia": 2.0,
      "enlargement": 0.0,
      "defence": 11.6,
      "energy": 2.0,
      "fiscal": 0.0,
      "rule_of_law": 13.1,
      "trade": 3.12,
      "total": 31.82
    },
    {
      "country": "NL",
      "migration": 0.0,
      "ukraine_russia": 17.4,
      "enlargement": 0.0,
      "defence": 100.67,
      "energy": 1.0,
      "fiscal": 0.0,
      "rule_of_law": 23.0,
      "trade": 45.37,
      "total": 187.44
    },
    {
      "country": "PL",
      "migration": 4.0,
      "ukraine_russia": 50.1,
      "enlargement": 0.0,
      "defence": 79.71,
      "energy": 5.0,
      "fiscal": 9.5,
      "rule_of_law": 0.0,
      "trade": 29.06,
      "total": 177.37
    },
    {
      "country": "PT",
      "migration": 0.0,
      "ukraine_russia": 0.0,
      "enlargement": 0.0,
      "defence": 41.82,
      "energy": 2.0,
      "fiscal": 7.6,
      "rule_of_law": 0.0,
      "trade": 11.42,
      "total": 62.84
    },
    {
      "country": "RO",
      "migration": 1.0,
      "ukraine_russia": 1.0,
      "enlargement": 0.0,
      "defence": 26.41,
      "energy": 1.0,
      "fiscal": 0.0,
      "rule_of_law": 7.1,
      "trade": 17.46,
      "total": 53.97
    },
    {
      "country": "RU",
      "migration": 25.0,
      "ukraine_russia": 781.2,
      "enlargement": 1.0,
      "defence": 183.14,
      "energy": 270.0,
      "fiscal": 34.0,
      "rule_of_law": 63.76,
      "trade": 93.19,
      "total": 1451.29
    },
    {
      "country": "SE",
      "migration": 1.0,
      "ukraine_russia": 5.0,
      "enlargement": 0.0,
      "defence": 40.86,
      "energy": 0.0,
      "fiscal": 0.0,
      "rule_of_law": 15.64,
      "trade": 28.12,
      "total": 90.62
    },
    {
      "country": "SI",
      "migration": 0.0,
      "ukraine_russia": 8.0,
      "enlargement": 0.0,
      "defence": 23.22,
      "energy": 9.0,
      "fiscal": 0.0,
      "rule_of_law": 33.1,
      "trade": 18.04,
      "total": 91.36
    },
    {
      "country": "SK",
      "migration": 2.0,
      "ukraine_russia": 44.0,
      "enlargement": 0.0,
      "defence": 23.7,
      "energy": 16.0,
      "fiscal": 0.0,
      "rule_of_law": 3.0,
      "trade": 4.52,
      "total": 93.22
    },
    {
      "country": "TR",
      "migration": 14.0,
      "ukraine_russia": 14.6,
      "enlargement": 0.0,
      "defence": 31.9,
      "energy": 6.0,
      "fiscal": 0.0,
      "rule_of_law": 16.9,
      "trade": 0.0,
      "total": 83.4
    },
    {
      "country": "UA",
      "migration": 25.0,
      "ukraine_russia": 727.7,
      "enlargement": 6.0,
      "defence": 261.62,
      "energy": 257.0,
      "fiscal": 34.0,
      "rule_of_law": 14.7,
      "trade": 105.86,
      "total": 1431.88
    },
    {
      "country": "US",
      "migration": 7.0,
      "ukraine_russia": 127.45,
      "enlargement": 0.0,
      "defence": 977.33,
      "energy": 25.0,
      "fiscal": 47.5,
      "rule_of_law": 117.35,
      "trade": 321.53,
      "total": 1623.16
    }
  ],
  "event_count": 2462,
  "mode": "all",
  "normalized": false
}